Kinho/__init__.py
Kinho/neural.py
Kinho/brain/__init__.py
Kinho/brain/builder.py
Kinho/brain/wrapper.py
Kinho/brain/decoder/__init__.py
Kinho/brain/decoder/d_float.py
Kinho/brain/decoder/d_int.py
Kinho/brain/decoder/d_string.py
Kinho/brain/encoder/__init__.py
Kinho/brain/encoder/e_float.py
Kinho/brain/encoder/e_int.py
Kinho/brain/encoder/e_string.py
Kinho/brain/encoder/e_xor.py
Kinho/kernel/__init__.py
Kinho/kernel/activation.py
Kinho/kernel/dactivation.py
Kinho/kernel/dlayer.py
Kinho/kernel/dloss.py
Kinho/kernel/dselector.py
Kinho/kernel/layer.py
Kinho/kernel/loss.py
Kinho/kernel/selector.py
Kinho/kernel/transpose.py
Kinho/kernel/updateWeights.py
Kinho/kernel/vars.py
Kinho/lib/__init__.py
Kinho/lib/GPU/CPU_version.py
Kinho/lib/GPU/Function.py
Kinho/lib/GPU/__init__.py
Kinho/lib/GPU/utils.py
Kinho/transfer/__init__.py
Kinho/transfer/loader.py
Kinho-2.1.0.dist-info/LICENSE
Kinho-2.1.0.dist-info/METADATA
Kinho-2.1.0.dist-info/WHEEL
Kinho-2.1.0.dist-info/top_level.txt
Kinho-2.1.0.dist-info/RECORD
