Metadata-Version: 2.1
Name: Kinho
Version: 2.1.0
Summary: A library to classify images with deep learning.
Home-page: https://github.com/kinhosz/Neural
Author: Kinhosz
Author-email: scruz.josecarlos@gmail.com
License: MIT
Keywords: dev,web
Classifier: Development Status :: 5 - Production/Stable
Classifier: Environment :: GPU
Classifier: Environment :: GPU :: NVIDIA CUDA
Classifier: Environment :: GPU :: NVIDIA CUDA :: 12 :: 12.0
Classifier: License :: OSI Approved :: MIT License
Classifier: Natural Language :: Portuguese (Brazilian)
Classifier: Natural Language :: English
Classifier: Programming Language :: Python
Classifier: Programming Language :: Python :: 3
Classifier: Topic :: Scientific/Engineering :: Artificial Intelligence
Classifier: Topic :: Scientific/Engineering :: Image Processing
Classifier: Topic :: Scientific/Engineering :: Image Recognition
License-File: LICENSE
